llms4pcg/__init__.py
llms4pcg/competition.py
llms4pcg/utils.py
llms4pcg/models/__init__.py
llms4pcg/models/trial_context.py
llms4pcg/models/trial_loop.py
llms4pcg-2.0.1.dist-info/licenses/LICENSE
llms4pcg-2.0.1.dist-info/METADATA
llms4pcg-2.0.1.dist-info/WHEEL
llms4pcg-2.0.1.dist-info/top_level.txt
llms4pcg-2.0.1.dist-info/RECORD
