Metadata-Version: 2.4
Name: llms4pcg
Version: 2.0.1
Summary: LLMs4PCG is a python package containing required and utility functions as a part of LLMs4PCG competition.
Author-email: LLMs4PCG Organizing Team <llm4pcg@ice.ci.ritsumei.ac.jp>, ChatGPT4PCG Organizing Team <chatgpt4pcg@gmail.com>, Pittawat Taveekitworachai <pittawat.pete@gmail.com>
Maintainer-email: LLMs4PCG Organizing Team <llm4pcg@ice.ci.ritsumei.ac.jp>, ChatGPT4PCG Organizing Team <chatgpt4pcg@gmail.com>
License: MIT License
Project-URL: Homepage, https://github.com/chatgpt4pcg
Project-URL: Bug Reports, https://github.com/chatgpt4pcg/llms4pcg-python/issues
Project-URL: Source, https://github.com/chatgpt4pcg/llms4pcg-python
Keywords: llms,llms4pcg,competition
Classifier: Development Status :: 5 - Production/Stable
Classifier: Intended Audience :: Developers
Classifier: Topic :: Software Development
Classifier: License :: OSI Approved :: MIT License
Classifier: Programming Language :: Python :: 3
Classifier: Programming Language :: Python :: 3.11
Classifier: Programming Language :: Python :: 3.12
Classifier: Programming Language :: Python :: 3 :: Only
Requires-Python: >=3.11
License-File: LICENSE
Requires-Dist: openai<2
Dynamic: license-file
